signal_petrophysics/__init__.py
signal_petrophysics/applications/depth_shifting.py
signal_petrophysics/load_data/__init__.py
signal_petrophysics/load_data/load_data.py
signal_petrophysics/pattern_find/__init__.py
signal_petrophysics/pattern_find/pattern_find.py
signal_petrophysics/plot/__init__.py
signal_petrophysics/plot/plot.py
signal_petrophysics/postprocessing/__init__.py
signal_petrophysics/postprocessing/postprocessing.py
signal_petrophysics/signal_adapt/__init__.py
signal_petrophysics/signal_adapt/signal_adapt.py
signal_petrophysics/utils/__init__.py
signal_petrophysics/utils/mnemonics.py
signal_petrophysics-0.0.1b34.dist-info/licenses/LICENSE
signal_petrophysics-0.0.1b34.dist-info/METADATA
signal_petrophysics-0.0.1b34.dist-info/WHEEL
signal_petrophysics-0.0.1b34.dist-info/top_level.txt
signal_petrophysics-0.0.1b34.dist-info/RECORD
