Metadata-Version: 2.4
Name: signal-petrophysics
Version: 0.0.1b34
Summary: Library to handle reading, analysing and plotting Well-Log Pattern Recognition algorithms from Signal-Processing
Author-email: Maria Fernanda Gonzalez <mariafgg@utexas.edu>
License: MIT
Project-URL: Homepage, https://github.com/mariafgg-utpge/Signal-Petrophysics
Project-URL: Repository, https://github.com/mariafgg-utpge/Signal-Petrophysics
Project-URL: Documentation, https://mariafgg-utpge.github.io/Signal-Petrophysics/
Project-URL: Bug Tracker, https://github.com/mariafgg-utpge/Signal-Petrophysics/issues
Classifier: Development Status :: 3 - Alpha
Classifier: Intended Audience :: Science/Research
Classifier: License :: OSI Approved :: MIT License
Classifier: Operating System :: OS Independent
Classifier: Programming Language :: Python :: 3
Classifier: Programming Language :: Python :: 3.10
Classifier: Programming Language :: Python :: 3.11
Classifier: Programming Language :: Python :: 3.12
Classifier: Topic :: Scientific/Engineering
Requires-Python: >=3.10
License-File: LICENSE
Requires-Dist: pandas>=2.0.1
Requires-Dist: scipy>=1.10.1
Requires-Dist: pyproj>=3.5.0
Provides-Extra: docs
Requires-Dist: mkdocs>=1.5.0; extra == "docs"
Requires-Dist: mkdocs-material>=9.0.0; extra == "docs"
Requires-Dist: mkdocstrings[python]>=0.24.0; extra == "docs"
Provides-Extra: dev
Requires-Dist: pytest>=7.0.0; extra == "dev"
Requires-Dist: black>=23.0.0; extra == "dev"
Requires-Dist: isort>=5.12.0; extra == "dev"
Requires-Dist: flake8>=6.0.0; extra == "dev"
Dynamic: license-file
